testsolar_pytestx/__init__.py
testsolar_pytestx/case_log.py
testsolar_pytestx/collector.py
testsolar_pytestx/conftest_generator.py
testsolar_pytestx/converter.py
testsolar_pytestx/executor.py
testsolar_pytestx/filter.py
testsolar_pytestx/header_injection.py
testsolar_pytestx/ini_fixer.py
testsolar_pytestx/parser.py
testsolar_pytestx/py.typed
testsolar_pytestx/stream.py
testsolar_pytestx/util.py
testsolar_pytestx/extend/__init__.py
testsolar_pytestx/extend/allure_extend.py
testsolar_pytestx/extend/coverage_extend.py
testsolar_pytestx-0.1.76.dist-info/METADATA
testsolar_pytestx-0.1.76.dist-info/WHEEL
testsolar_pytestx-0.1.76.dist-info/RECORD
